<?xml version="1.0" encoding="utf-8"?>
<DatesCommandes>
	<DateCommande Année="1996" Mois="7">
		<Commande Id="10248" Montant="440,00" />
		<Commande Id="10249" Montant="1863,40" />
		<Commande Id="10250" Montant="1552,60" />
		<Commande Id="10251" Montant="654,06" />
		<Commande Id="10252" Montant="3597,90" />
		<Commande Id="10253" Montant="1444,80" />
		<Commande Id="10254" Montant="556,62" />
		<Commande Id="10255" Montant="2490,50" />
		<Commande Id="10256" Montant="517,80" />
		<Commande Id="10257" Montant="1119,90" />
		<Commande Id="10258" Montant="1614,88" />
		<Commande Id="10259" Montant="100,80" />
		<Commande Id="10260" Montant="1504,65" />
		<Commande Id="10261" Montant="448,00" />
		<Commande Id="10262" Montant="584,00" />
		<Commande Id="10263" Montant="1873,80" />
		<Commande Id="10264" Montant="695,63" />
		<Commande Id="10265" Montant="1176,00" />
		<Commande Id="10266" Montant="346,56" />
		<Commande Id="10267" Montant="3536,60" />
		<Commande Id="10268" Montant="1101,20" />
		<Commande Id="10269" Montant="642,20" />
	</DateCommande>
	<DateCommande Année="1996" Mois="8">
		<Commande Id="10270" Montant="1376,00" />
		<Commande Id="10271" Montant="48,00" />
		<Commande Id="10272" Montant="1456,00" />
		<Commande Id="10273" Montant="2037,28" />
		<Commande Id="10274" Montant="538,60" />
		<Commande Id="10275" Montant="291,84" />
		<Commande Id="10276" Montant="420,00" />
		<Commande Id="10277" Montant="1200,80" />
		<Commande Id="10278" Montant="1488,80" />
		<Commande Id="10279" Montant="351,00" />
		<Commande Id="10280" Montant="613,20" />
		<Commande Id="10281" Montant="86,50" />
		<Commande Id="10282" Montant="155,40" />
		<Commande Id="10283" Montant="1414,80" />
		<Commande Id="10284" Montant="1170,38" />
		<Commande Id="10285" Montant="1743,36" />
		<Commande Id="10286" Montant="3016,00" />
		<Commande Id="10287" Montant="819,00" />
		<Commande Id="10288" Montant="80,10" />
		<Commande Id="10289" Montant="479,40" />
		<Commande Id="10290" Montant="2169,00" />
		<Commande Id="10291" Montant="497,52" />
		<Commande Id="10292" Montant="1296,00" />
		<Commande Id="10293" Montant="848,70" />
		<Commande Id="10294" Montant="1887,60" />
	</DateCommande>
	<DateCommande Année="1996" Mois="9">
		<Commande Id="10295" Montant="121,60" />
		<Commande Id="10296" Montant="1050,60" />
		<Commande Id="10297" Montant="1420,00" />
		<Commande Id="10298" Montant="2645,00" />
		<Commande Id="10299" Montant="349,50" />
		<Commande Id="10300" Montant="608,00" />
		<Commande Id="10301" Montant="755,00" />
		<Commande Id="10302" Montant="2708,80" />
		<Commande Id="10303" Montant="1117,80" />
		<Commande Id="10304" Montant="954,40" />
		<Commande Id="10305" Montant="3741,30" />
		<Commande Id="10306" Montant="498,50" />
		<Commande Id="10307" Montant="424,00" />
		<Commande Id="10308" Montant="88,80" />
		<Commande Id="10309" Montant="1762,00" />
		<Commande Id="10310" Montant="336,00" />
		<Commande Id="10311" Montant="268,80" />
		<Commande Id="10312" Montant="1614,80" />
		<Commande Id="10313" Montant="182,40" />
		<Commande Id="10314" Montant="2094,30" />
		<Commande Id="10315" Montant="516,80" />
		<Commande Id="10316" Montant="2835,00" />
		<Commande Id="10317" Montant="288,00" />
	</DateCommande>
	<DateCommande Année="1996" Mois="10">
		<Commande Id="10318" Montant="240,40" />
		<Commande Id="10319" Montant="1191,20" />
		<Commande Id="10320" Montant="516,00" />
		<Commande Id="10321" Montant="144,00" />
		<Commande Id="10322" Montant="112,00" />
		<Commande Id="10323" Montant="164,40" />
		<Commande Id="10324" Montant="5275,72" />
		<Commande Id="10325" Montant="1497,00" />
		<Commande Id="10326" Montant="982,00" />
		<Commande Id="10327" Montant="1810,00" />
		<Commande Id="10328" Montant="1168,00" />
		<Commande Id="10329" Montant="4578,43" />
		<Commande Id="10330" Montant="1649,00" />
		<Commande Id="10331" Montant="88,50" />
		<Commande Id="10332" Montant="1786,88" />
		<Commande Id="10333" Montant="877,20" />
		<Commande Id="10334" Montant="144,80" />
		<Commande Id="10335" Montant="2036,16" />
		<Commande Id="10336" Montant="285,12" />
		<Commande Id="10337" Montant="2467,00" />
		<Commande Id="10338" Montant="934,50" />
		<Commande Id="10339" Montant="3354,00" />
		<Commande Id="10340" Montant="2436,18" />
		<Commande Id="10341" Montant="352,60" />
		<Commande Id="10342" Montant="1840,64" />
		<Commande Id="10343" Montant="1584,00" />
	</DateCommande>
	<DateCommande Année="1996" Mois="11">
		<Commande Id="10344" Montant="2296,00" />
		<Commande Id="10345" Montant="2924,80" />
		<Commande Id="10346" Montant="1618,88" />
		<Commande Id="10347" Montant="814,42" />
		<Commande Id="10348" Montant="363,60" />
		<Commande Id="10349" Montant="141,60" />
		<Commande Id="10350" Montant="642,06" />
		<Commande Id="10351" Montant="5398,73" />
		<Commande Id="10352" Montant="136,30" />
		<Commande Id="10353" Montant="8593,28" />
		<Commande Id="10354" Montant="568,80" />
		<Commande Id="10355" Montant="480,00" />
		<Commande Id="10356" Montant="1106,40" />
		<Commande Id="10357" Montant="1167,68" />
		<Commande Id="10358" Montant="429,40" />
		<Commande Id="10359" Montant="3471,68" />
		<Commande Id="10360" Montant="7390,20" />
		<Commande Id="10361" Montant="2046,24" />
		<Commande Id="10362" Montant="1549,60" />
		<Commande Id="10363" Montant="447,20" />
		<Commande Id="10364" Montant="950,00" />
		<Commande Id="10365" Montant="403,20" />
		<Commande Id="10366" Montant="136,00" />
		<Commande Id="10367" Montant="834,20" />
		<Commande Id="10368" Montant="1689,78" />
	</DateCommande>
	<DateCommande Année="1996" Mois="12">
		<Commande Id="10369" Montant="2390,40" />
		<Commande Id="10370" Montant="1117,60" />
		<Commande Id="10371" Montant="72,96" />
		<Commande Id="10372" Montant="9210,90" />
		<Commande Id="10373" Montant="1366,40" />
		<Commande Id="10374" Montant="459,00" />
		<Commande Id="10375" Montant="338,00" />
		<Commande Id="10376" Montant="399,00" />
		<Commande Id="10377" Montant="863,60" />
		<Commande Id="10378" Montant="103,20" />
		<Commande Id="10379" Montant="863,28" />
		<Commande Id="10380" Montant="1313,82" />
		<Commande Id="10381" Montant="112,00" />
		<Commande Id="10382" Montant="2900,00" />
		<Commande Id="10383" Montant="899,00" />
		<Commande Id="10384" Montant="2222,40" />
		<Commande Id="10385" Montant="691,20" />
		<Commande Id="10386" Montant="166,00" />
		<Commande Id="10387" Montant="1058,40" />
		<Commande Id="10388" Montant="1228,80" />
		<Commande Id="10389" Montant="1832,80" />
		<Commande Id="10390" Montant="2090,88" />
		<Commande Id="10391" Montant="86,40" />
		<Commande Id="10392" Montant="1440,00" />
		<Commande Id="10393" Montant="2556,95" />
		<Commande Id="10394" Montant="442,00" />
		<Commande Id="10395" Montant="2122,92" />
		<Commande Id="10396" Montant="1903,80" />
		<Commande Id="10397" Montant="716,72" />
		<Commande Id="10398" Montant="2505,60" />
		<Commande Id="10399" Montant="1765,60" />
	</DateCommande>
	<DateCommande Année="1997" Mois="1">
		<Commande Id="10400" Montant="3063,00" />
		<Commande Id="10401" Montant="3868,60" />
		<Commande Id="10402" Montant="2713,50" />
		<Commande Id="10403" Montant="855,02" />
		<Commande Id="10404" Montant="1591,25" />
		<Commande Id="10405" Montant="400,00" />
		<Commande Id="10406" Montant="1830,78" />
		<Commande Id="10407" Montant="1194,00" />
		<Commande Id="10408" Montant="1622,40" />
		<Commande Id="10409" Montant="319,20" />
		<Commande Id="10410" Montant="802,00" />
		<Commande Id="10411" Montant="966,80" />
		<Commande Id="10412" Montant="334,80" />
		<Commande Id="10413" Montant="2123,20" />
		<Commande Id="10414" Montant="224,83" />
		<Commande Id="10415" Montant="102,40" />
		<Commande Id="10416" Montant="720,00" />
		<Commande Id="10417" Montant="11188,40" />
		<Commande Id="10418" Montant="1814,80" />
		<Commande Id="10419" Montant="2097,60" />
		<Commande Id="10420" Montant="1707,84" />
		<Commande Id="10421" Montant="1194,27" />
		<Commande Id="10422" Montant="49,80" />
		<Commande Id="10423" Montant="1020,00" />
		<Commande Id="10424" Montant="9194,56" />
		<Commande Id="10425" Montant="360,00" />
		<Commande Id="10426" Montant="338,20" />
		<Commande Id="10427" Montant="651,00" />
		<Commande Id="10428" Montant="192,00" />
		<Commande Id="10429" Montant="1441,38" />
		<Commande Id="10430" Montant="4899,20" />
		<Commande Id="10431" Montant="1892,25" />
		<Commande Id="10432" Montant="485,00" />
	</DateCommande>
	<DateCommande Année="1997" Mois="2">
		<Commande Id="10433" Montant="851,20" />
		<Commande Id="10434" Montant="321,12" />
		<Commande Id="10435" Montant="631,60" />
		<Commande Id="10436" Montant="1994,52" />
		<Commande Id="10437" Montant="393,00" />
		<Commande Id="10438" Montant="454,00" />
		<Commande Id="10439" Montant="1078,00" />
		<Commande Id="10440" Montant="4924,14" />
		<Commande Id="10441" Montant="1755,00" />
		<Commande Id="10442" Montant="1792,00" />
		<Commande Id="10443" Montant="517,44" />
		<Commande Id="10444" Montant="1031,70" />
		<Commande Id="10445" Montant="174,90" />
		<Commande Id="10446" Montant="246,24" />
		<Commande Id="10447" Montant="914,40" />
		<Commande Id="10448" Montant="443,40" />
		<Commande Id="10449" Montant="1838,20" />
		<Commande Id="10450" Montant="425,12" />
		<Commande Id="10451" Montant="3849,66" />
		<Commande Id="10452" Montant="2018,50" />
		<Commande Id="10453" Montant="407,70" />
		<Commande Id="10454" Montant="331,20" />
		<Commande Id="10455" Montant="2684,00" />
		<Commande Id="10456" Montant="557,60" />
		<Commande Id="10457" Montant="1584,00" />
		<Commande Id="10458" Montant="3891,00" />
		<Commande Id="10459" Montant="1659,20" />
		<Commande Id="10460" Montant="176,10" />
		<Commande Id="10461" Montant="1538,70" />
	</DateCommande>
	<DateCommande Année="1997" Mois="3">
		<Commande Id="10462" Montant="156,00" />
		<Commande Id="10463" Montant="713,30" />
		<Commande Id="10464" Montant="1609,28" />
		<Commande Id="10465" Montant="2518,00" />
		<Commande Id="10466" Montant="216,00" />
		<Commande Id="10467" Montant="235,20" />
		<Commande Id="10468" Montant="717,60" />
		<Commande Id="10469" Montant="956,68" />
		<Commande Id="10470" Montant="1820,80" />
		<Commande Id="10471" Montant="1328,00" />
		<Commande Id="10472" Montant="1036,80" />
		<Commande Id="10473" Montant="230,40" />
		<Commande Id="10474" Montant="1249,10" />
		<Commande Id="10475" Montant="1505,18" />
		<Commande Id="10476" Montant="180,48" />
		<Commande Id="10477" Montant="558,00" />
		<Commande Id="10478" Montant="471,20" />
		<Commande Id="10479" Montant="10495,60" />
		<Commande Id="10480" Montant="756,00" />
		<Commande Id="10481" Montant="1472,00" />
		<Commande Id="10482" Montant="147,00" />
		<Commande Id="10483" Montant="668,80" />
		<Commande Id="10484" Montant="386,20" />
		<Commande Id="10485" Montant="1584,00" />
		<Commande Id="10486" Montant="1272,00" />
		<Commande Id="10487" Montant="889,70" />
		<Commande Id="10488" Montant="1512,00" />
		<Commande Id="10489" Montant="439,20" />
		<Commande Id="10490" Montant="3163,20" />
		<Commande Id="10491" Montant="259,51" />
	</DateCommande>
	<DateCommande Année="1997" Mois="4">
		<Commande Id="10492" Montant="851,20" />
		<Commande Id="10493" Montant="608,40" />
		<Commande Id="10494" Montant="912,00" />
		<Commande Id="10495" Montant="278,00" />
		<Commande Id="10496" Montant="190,00" />
		<Commande Id="10497" Montant="1380,60" />
		<Commande Id="10498" Montant="575,00" />
		<Commande Id="10499" Montant="1412,00" />
		<Commande Id="10500" Montant="523,26" />
		<Commande Id="10501" Montant="149,00" />
		<Commande Id="10502" Montant="816,30" />
		<Commande Id="10503" Montant="2048,50" />
		<Commande Id="10504" Montant="1388,50" />
		<Commande Id="10505" Montant="147,90" />
		<Commande Id="10506" Montant="415,80" />
		<Commande Id="10507" Montant="749,06" />
		<Commande Id="10508" Montant="240,00" />
		<Commande Id="10509" Montant="136,80" />
		<Commande Id="10510" Montant="4707,54" />
		<Commande Id="10511" Montant="2550,00" />
		<Commande Id="10512" Montant="525,30" />
		<Commande Id="10513" Montant="1942,00" />
		<Commande Id="10514" Montant="8623,45" />
		<Commande Id="10515" Montant="9921,30" />
		<Commande Id="10516" Montant="2381,05" />
		<Commande Id="10517" Montant="352,00" />
		<Commande Id="10518" Montant="4150,05" />
		<Commande Id="10519" Montant="2314,20" />
		<Commande Id="10520" Montant="200,00" />
		<Commande Id="10521" Montant="225,50" />
		<Commande Id="10522" Montant="2318,24" />
	</DateCommande>
	<DateCommande Année="1997" Mois="5">
		<Commande Id="10523" Montant="2444,31" />
		<Commande Id="10524" Montant="3192,65" />
		<Commande Id="10525" Montant="818,40" />
		<Commande Id="10526" Montant="1151,40" />
		<Commande Id="10527" Montant="1503,00" />
		<Commande Id="10528" Montant="392,20" />
		<Commande Id="10529" Montant="946,00" />
		<Commande Id="10530" Montant="4180,00" />
		<Commande Id="10531" Montant="110,00" />
		<Commande Id="10532" Montant="796,35" />
		<Commande Id="10533" Montant="2222,20" />
		<Commande Id="10534" Montant="465,70" />
		<Commande Id="10535" Montant="1940,85" />
		<Commande Id="10536" Montant="1645,00" />
		<Commande Id="10537" Montant="1823,80" />
		<Commande Id="10538" Montant="139,80" />
		<Commande Id="10539" Montant="355,50" />
		<Commande Id="10540" Montant="10191,70" />
		<Commande Id="10541" Montant="1946,52" />
		<Commande Id="10542" Montant="469,11" />
		<Commande Id="10543" Montant="1504,50" />
		<Commande Id="10544" Montant="417,20" />
		<Commande Id="10545" Montant="210,00" />
		<Commande Id="10546" Montant="2812,00" />
		<Commande Id="10547" Montant="1792,80" />
		<Commande Id="10548" Montant="240,10" />
		<Commande Id="10549" Montant="3554,28" />
		<Commande Id="10550" Montant="683,30" />
		<Commande Id="10551" Montant="1677,30" />
		<Commande Id="10552" Montant="880,50" />
		<Commande Id="10553" Montant="1546,30" />
		<Commande Id="10554" Montant="1728,53" />
	</DateCommande>
	<DateCommande Année="1997" Mois="6">
		<Commande Id="10555" Montant="2944,40" />
		<Commande Id="10556" Montant="835,20" />
		<Commande Id="10557" Montant="1152,50" />
		<Commande Id="10558" Montant="2142,90" />
		<Commande Id="10559" Montant="520,41" />
		<Commande Id="10560" Montant="1072,43" />
		<Commande Id="10561" Montant="2844,50" />
		<Commande Id="10562" Montant="488,70" />
		<Commande Id="10563" Montant="965,00" />
		<Commande Id="10564" Montant="1234,05" />
		<Commande Id="10565" Montant="639,90" />
		<Commande Id="10566" Montant="1761,00" />
		<Commande Id="10567" Montant="2519,00" />
		<Commande Id="10568" Montant="155,00" />
		<Commande Id="10569" Montant="890,00" />
		<Commande Id="10570" Montant="2465,25" />
		<Commande Id="10571" Montant="550,59" />
		<Commande Id="10572" Montant="1501,09" />
		<Commande Id="10573" Montant="2082,00" />
		<Commande Id="10574" Montant="764,30" />
		<Commande Id="10575" Montant="2147,40" />
		<Commande Id="10576" Montant="838,45" />
		<Commande Id="10577" Montant="569,00" />
		<Commande Id="10578" Montant="477,00" />
		<Commande Id="10579" Montant="317,75" />
		<Commande Id="10580" Montant="1013,75" />
		<Commande Id="10581" Montant="310,00" />
		<Commande Id="10582" Montant="330,00" />
		<Commande Id="10583" Montant="2237,50" />
		<Commande Id="10584" Montant="593,75" />
	</DateCommande>
	<DateCommande Année="1997" Mois="7">
		<Commande Id="10585" Montant="142,50" />
		<Commande Id="10586" Montant="23,80" />
		<Commande Id="10587" Montant="807,38" />
		<Commande Id="10588" Montant="3120,00" />
		<Commande Id="10589" Montant="72,00" />
		<Commande Id="10590" Montant="1101,00" />
		<Commande Id="10591" Montant="812,50" />
		<Commande Id="10592" Montant="516,47" />
		<Commande Id="10593" Montant="1994,40" />
		<Commande Id="10594" Montant="565,50" />
		<Commande Id="10595" Montant="4725,00" />
		<Commande Id="10596" Montant="1180,88" />
		<Commande Id="10597" Montant="718,08" />
		<Commande Id="10598" Montant="2388,50" />
		<Commande Id="10599" Montant="493,00" />
		<Commande Id="10600" Montant="479,80" />
		<Commande Id="10601" Montant="2285,00" />
		<Commande Id="10602" Montant="48,75" />
		<Commande Id="10603" Montant="1483,00" />
		<Commande Id="10604" Montant="230,85" />
		<Commande Id="10605" Montant="4109,70" />
		<Commande Id="10606" Montant="1130,40" />
		<Commande Id="10607" Montant="6475,40" />
		<Commande Id="10608" Montant="1064,00" />
		<Commande Id="10609" Montant="424,00" />
		<Commande Id="10610" Montant="299,25" />
		<Commande Id="10611" Montant="808,00" />
		<Commande Id="10612" Montant="6375,00" />
		<Commande Id="10613" Montant="353,20" />
		<Commande Id="10614" Montant="464,00" />
		<Commande Id="10615" Montant="120,00" />
		<Commande Id="10616" Montant="4807,00" />
		<Commande Id="10617" Montant="1402,50" />
	</DateCommande>
	<DateCommande Année="1997" Mois="8">
		<Commande Id="10618" Montant="2697,50" />
		<Commande Id="10619" Montant="1260,00" />
		<Commande Id="10620" Montant="57,50" />
		<Commande Id="10621" Montant="758,50" />
		<Commande Id="10622" Montant="560,00" />
		<Commande Id="10623" Montant="1336,95" />
		<Commande Id="10624" Montant="1393,24" />
		<Commande Id="10625" Montant="479,75" />
		<Commande Id="10626" Montant="1503,60" />
		<Commande Id="10627" Montant="1185,75" />
		<Commande Id="10628" Montant="450,00" />
		<Commande Id="10629" Montant="2775,05" />
		<Commande Id="10630" Montant="903,60" />
		<Commande Id="10631" Montant="55,80" />
		<Commande Id="10632" Montant="589,00" />
		<Commande Id="10633" Montant="5510,59" />
		<Commande Id="10634" Montant="4985,50" />
		<Commande Id="10635" Montant="1326,23" />
		<Commande Id="10636" Montant="629,50" />
		<Commande Id="10637" Montant="2761,94" />
		<Commande Id="10638" Montant="2720,05" />
		<Commande Id="10639" Montant="500,00" />
		<Commande Id="10640" Montant="708,75" />
		<Commande Id="10641" Montant="2054,00" />
		<Commande Id="10642" Montant="696,00" />
		<Commande Id="10643" Montant="814,50" />
		<Commande Id="10644" Montant="1371,80" />
		<Commande Id="10645" Montant="1535,00" />
		<Commande Id="10646" Montant="1446,00" />
		<Commande Id="10647" Montant="636,00" />
		<Commande Id="10648" Montant="372,38" />
		<Commande Id="10649" Montant="1434,00" />
		<Commande Id="10650" Montant="1779,20" />
	</DateCommande>
	<DateCommande Année="1997" Mois="9">
		<Commande Id="10651" Montant="397,80" />
		<Commande Id="10652" Montant="318,84" />
		<Commande Id="10653" Montant="1083,15" />
		<Commande Id="10654" Montant="601,83" />
		<Commande Id="10655" Montant="154,40" />
		<Commande Id="10656" Montant="604,22" />
		<Commande Id="10657" Montant="4371,60" />
		<Commande Id="10658" Montant="4464,60" />
		<Commande Id="10659" Montant="1227,02" />
		<Commande Id="10660" Montant="1701,00" />
		<Commande Id="10661" Montant="562,60" />
		<Commande Id="10662" Montant="125,00" />
		<Commande Id="10663" Montant="1930,40" />
		<Commande Id="10664" Montant="1288,39" />
		<Commande Id="10665" Montant="1295,00" />
		<Commande Id="10666" Montant="4666,94" />
		<Commande Id="10667" Montant="1536,80" />
		<Commande Id="10668" Montant="625,28" />
		<Commande Id="10669" Montant="570,00" />
		<Commande Id="10670" Montant="2301,75" />
		<Commande Id="10671" Montant="920,10" />
		<Commande Id="10672" Montant="3815,25" />
		<Commande Id="10673" Montant="412,35" />
		<Commande Id="10674" Montant="45,00" />
		<Commande Id="10675" Montant="1423,00" />
		<Commande Id="10676" Montant="534,85" />
		<Commande Id="10677" Montant="813,37" />
		<Commande Id="10678" Montant="5256,50" />
		<Commande Id="10679" Montant="660,00" />
		<Commande Id="10680" Montant="1261,88" />
		<Commande Id="10681" Montant="1287,40" />
		<Commande Id="10682" Montant="375,50" />
		<Commande Id="10683" Montant="63,00" />
		<Commande Id="10684" Montant="1768,00" />
		<Commande Id="10685" Montant="801,10" />
		<Commande Id="10686" Montant="1404,45" />
		<Commande Id="10687" Montant="4960,90" />
	</DateCommande>
	<DateCommande Année="1997" Mois="10">
		<Commande Id="10688" Montant="3160,60" />
		<Commande Id="10689" Montant="472,50" />
		<Commande Id="10690" Montant="862,50" />
		<Commande Id="10691" Montant="10164,80" />
		<Commande Id="10692" Montant="878,00" />
		<Commande Id="10693" Montant="2071,20" />
		<Commande Id="10694" Montant="4825,00" />
		<Commande Id="10695" Montant="642,00" />
		<Commande Id="10696" Montant="996,00" />
		<Commande Id="10697" Montant="805,43" />
		<Commande Id="10698" Montant="3436,44" />
		<Commande Id="10699" Montant="114,00" />
		<Commande Id="10700" Montant="1638,40" />
		<Commande Id="10701" Montant="2864,50" />
		<Commande Id="10702" Montant="330,00" />
		<Commande Id="10703" Montant="2545,00" />
		<Commande Id="10704" Montant="595,50" />
		<Commande Id="10705" Montant="378,00" />
		<Commande Id="10706" Montant="1893,00" />
		<Commande Id="10707" Montant="1641,00" />
		<Commande Id="10708" Montant="180,40" />
		<Commande Id="10709" Montant="3424,00" />
		<Commande Id="10710" Montant="93,50" />
		<Commande Id="10711" Montant="4451,70" />
		<Commande Id="10712" Montant="1233,48" />
		<Commande Id="10713" Montant="2827,90" />
		<Commande Id="10714" Montant="2205,75" />
		<Commande Id="10715" Montant="1296,00" />
		<Commande Id="10716" Montant="706,00" />
		<Commande Id="10717" Montant="1270,75" />
		<Commande Id="10718" Montant="3463,00" />
		<Commande Id="10719" Montant="844,25" />
		<Commande Id="10720" Montant="550,00" />
		<Commande Id="10721" Montant="923,88" />
		<Commande Id="10722" Montant="1570,00" />
		<Commande Id="10723" Montant="468,45" />
		<Commande Id="10724" Montant="638,50" />
		<Commande Id="10725" Montant="287,80" />
	</DateCommande>
	<DateCommande Année="1997" Mois="11">
		<Commande Id="10726" Montant="655,00" />
		<Commande Id="10727" Montant="1624,50" />
		<Commande Id="10728" Montant="1296,75" />
		<Commande Id="10729" Montant="1850,00" />
		<Commande Id="10730" Montant="484,26" />
		<Commande Id="10731" Montant="1890,50" />
		<Commande Id="10732" Montant="360,00" />
		<Commande Id="10733" Montant="1459,00" />
		<Commande Id="10734" Montant="1498,35" />
		<Commande Id="10735" Montant="536,40" />
		<Commande Id="10736" Montant="997,00" />
		<Commande Id="10737" Montant="139,80" />
		<Commande Id="10738" Montant="52,35" />
		<Commande Id="10739" Montant="240,00" />
		<Commande Id="10740" Montant="1416,00" />
		<Commande Id="10741" Montant="228,00" />
		<Commande Id="10742" Montant="3118,00" />
		<Commande Id="10743" Montant="319,20" />
		<Commande Id="10744" Montant="736,00" />
		<Commande Id="10745" Montant="4529,80" />
		<Commande Id="10746" Montant="2311,70" />
		<Commande Id="10747" Montant="1912,85" />
		<Commande Id="10748" Montant="2196,00" />
		<Commande Id="10749" Montant="1080,00" />
		<Commande Id="10750" Montant="1590,56" />
		<Commande Id="10751" Montant="1631,48" />
		<Commande Id="10752" Montant="252,00" />
		<Commande Id="10753" Montant="88,00" />
		<Commande Id="10754" Montant="55,20" />
		<Commande Id="10755" Montant="1948,50" />
		<Commande Id="10756" Montant="1990,00" />
		<Commande Id="10757" Montant="3082,00" />
		<Commande Id="10758" Montant="1644,60" />
		<Commande Id="10759" Montant="320,00" />
	</DateCommande>
	<DateCommande Année="1997" Mois="12">
		<Commande Id="10760" Montant="2917,00" />
		<Commande Id="10761" Montant="507,00" />
		<Commande Id="10762" Montant="4337,00" />
		<Commande Id="10763" Montant="616,00" />
		<Commande Id="10764" Montant="2286,00" />
		<Commande Id="10765" Montant="1515,60" />
		<Commande Id="10766" Montant="2310,00" />
		<Commande Id="10767" Montant="28,00" />
		<Commande Id="10768" Montant="1477,00" />
		<Commande Id="10769" Montant="1684,28" />
		<Commande Id="10770" Montant="236,25" />
		<Commande Id="10771" Montant="344,00" />
		<Commande Id="10772" Montant="3603,22" />
		<Commande Id="10773" Montant="2030,40" />
		<Commande Id="10774" Montant="868,75" />
		<Commande Id="10775" Montant="228,00" />
		<Commande Id="10776" Montant="6635,28" />
		<Commande Id="10777" Montant="224,00" />
		<Commande Id="10778" Montant="96,50" />
		<Commande Id="10779" Montant="1335,00" />
		<Commande Id="10780" Montant="720,00" />
		<Commande Id="10781" Montant="975,88" />
		<Commande Id="10782" Montant="12,50" />
		<Commande Id="10783" Montant="1442,50" />
		<Commande Id="10784" Montant="1488,00" />
		<Commande Id="10785" Montant="387,50" />
		<Commande Id="10786" Montant="1531,08" />
		<Commande Id="10787" Montant="2622,76" />
		<Commande Id="10788" Montant="731,50" />
		<Commande Id="10789" Montant="3687,00" />
		<Commande Id="10790" Montant="722,50" />
		<Commande Id="10791" Montant="1829,76" />
		<Commande Id="10792" Montant="399,85" />
		<Commande Id="10793" Montant="191,10" />
		<Commande Id="10794" Montant="314,76" />
		<Commande Id="10795" Montant="2158,00" />
		<Commande Id="10796" Montant="2341,36" />
		<Commande Id="10797" Montant="420,00" />
		<Commande Id="10798" Montant="446,60" />
		<Commande Id="10799" Montant="1553,50" />
		<Commande Id="10800" Montant="1468,94" />
		<Commande Id="10801" Montant="3026,85" />
		<Commande Id="10802" Montant="2942,81" />
		<Commande Id="10803" Montant="1193,01" />
		<Commande Id="10804" Montant="2278,40" />
		<Commande Id="10805" Montant="2775,00" />
		<Commande Id="10806" Montant="439,60" />
		<Commande Id="10807" Montant="18,40" />
	</DateCommande>
	<DateCommande Année="1998" Mois="1">
		<Commande Id="10808" Montant="1411,00" />
		<Commande Id="10809" Montant="140,00" />
		<Commande Id="10810" Montant="187,00" />
		<Commande Id="10811" Montant="852,00" />
		<Commande Id="10812" Montant="1692,80" />
		<Commande Id="10813" Montant="602,40" />
		<Commande Id="10814" Montant="1788,45" />
		<Commande Id="10815" Montant="40,00" />
		<Commande Id="10816" Montant="8446,45" />
		<Commande Id="10817" Montant="10952,85" />
		<Commande Id="10818" Montant="833,00" />
		<Commande Id="10819" Montant="477,00" />
		<Commande Id="10820" Montant="1140,00" />
		<Commande Id="10821" Montant="678,00" />
		<Commande Id="10822" Montant="237,90" />
		<Commande Id="10823" Montant="2826,00" />
		<Commande Id="10824" Montant="250,80" />
		<Commande Id="10825" Montant="1030,76" />
		<Commande Id="10826" Montant="730,00" />
		<Commande Id="10827" Montant="843,00" />
		<Commande Id="10828" Montant="932,00" />
		<Commande Id="10829" Montant="1764,00" />
		<Commande Id="10830" Montant="1974,00" />
		<Commande Id="10831" Montant="2684,40" />
		<Commande Id="10832" Montant="475,11" />
		<Commande Id="10833" Montant="906,93" />
		<Commande Id="10834" Montant="1432,71" />
		<Commande Id="10835" Montant="845,80" />
		<Commande Id="10836" Montant="4705,50" />
		<Commande Id="10837" Montant="1064,50" />
		<Commande Id="10838" Montant="1938,38" />
		<Commande Id="10839" Montant="827,55" />
		<Commande Id="10840" Montant="211,20" />
		<Commande Id="10841" Montant="4581,00" />
		<Commande Id="10842" Montant="975,00" />
		<Commande Id="10843" Montant="159,00" />
		<Commande Id="10844" Montant="735,00" />
		<Commande Id="10845" Montant="3812,70" />
		<Commande Id="10846" Montant="1112,00" />
		<Commande Id="10847" Montant="4931,92" />
		<Commande Id="10848" Montant="931,50" />
		<Commande Id="10849" Montant="967,82" />
		<Commande Id="10850" Montant="629,00" />
		<Commande Id="10851" Montant="2603,00" />
		<Commande Id="10852" Montant="2984,00" />
		<Commande Id="10853" Montant="625,00" />
		<Commande Id="10854" Montant="2966,50" />
		<Commande Id="10855" Montant="2227,89" />
		<Commande Id="10856" Montant="660,00" />
		<Commande Id="10857" Montant="2048,21" />
		<Commande Id="10858" Montant="649,00" />
		<Commande Id="10859" Montant="1078,69" />
		<Commande Id="10860" Montant="519,00" />
		<Commande Id="10861" Montant="3523,40" />
		<Commande Id="10862" Montant="581,00" />
	</DateCommande>
	<DateCommande Année="1998" Mois="2">
		<Commande Id="10863" Montant="441,15" />
		<Commande Id="10864" Montant="282,00" />
		<Commande Id="10865" Montant="16387,50" />
		<Commande Id="10866" Montant="1096,20" />
		<Commande Id="10867" Montant="98,40" />
		<Commande Id="10868" Montant="1920,60" />
		<Commande Id="10869" Montant="1630,00" />
		<Commande Id="10870" Montant="160,00" />
		<Commande Id="10871" Montant="1979,23" />
		<Commande Id="10872" Montant="2058,46" />
		<Commande Id="10873" Montant="336,80" />
		<Commande Id="10874" Montant="310,00" />
		<Commande Id="10875" Montant="709,55" />
		<Commande Id="10876" Montant="917,00" />
		<Commande Id="10877" Montant="1955,13" />
		<Commande Id="10878" Montant="1539,00" />
		<Commande Id="10879" Montant="611,30" />
		<Commande Id="10880" Montant="1500,00" />
		<Commande Id="10881" Montant="150,00" />
		<Commande Id="10882" Montant="892,64" />
		<Commande Id="10883" Montant="36,00" />
		<Commande Id="10884" Montant="1378,07" />
		<Commande Id="10885" Montant="1209,00" />
		<Commande Id="10886" Montant="3127,50" />
		<Commande Id="10887" Montant="70,00" />
		<Commande Id="10888" Montant="605,00" />
		<Commande Id="10889" Montant="11380,00" />
		<Commande Id="10890" Montant="860,10" />
		<Commande Id="10891" Montant="368,93" />
		<Commande Id="10892" Montant="2090,00" />
		<Commande Id="10893" Montant="5502,11" />
		<Commande Id="10894" Montant="2753,10" />
		<Commande Id="10895" Montant="6379,40" />
		<Commande Id="10896" Montant="750,50" />
		<Commande Id="10897" Montant="10835,24" />
		<Commande Id="10898" Montant="30,00" />
		<Commande Id="10899" Montant="122,40" />
		<Commande Id="10900" Montant="33,75" />
		<Commande Id="10901" Montant="934,50" />
		<Commande Id="10902" Montant="863,43" />
		<Commande Id="10903" Montant="932,05" />
		<Commande Id="10904" Montant="1924,25" />
		<Commande Id="10905" Montant="342,00" />
		<Commande Id="10906" Montant="427,50" />
		<Commande Id="10907" Montant="108,50" />
		<Commande Id="10908" Montant="663,10" />
		<Commande Id="10909" Montant="670,00" />
		<Commande Id="10910" Montant="452,90" />
		<Commande Id="10911" Montant="858,00" />
		<Commande Id="10912" Montant="6200,55" />
		<Commande Id="10913" Montant="768,75" />
		<Commande Id="10914" Montant="537,50" />
		<Commande Id="10915" Montant="539,50" />
		<Commande Id="10916" Montant="686,70" />
	</DateCommande>
	<DateCommande Année="1998" Mois="3">
		<Commande Id="10917" Montant="365,89" />
		<Commande Id="10918" Montant="1447,50" />
		<Commande Id="10919" Montant="1122,80" />
		<Commande Id="10920" Montant="390,00" />
		<Commande Id="10921" Montant="1936,00" />
		<Commande Id="10922" Montant="742,50" />
		<Commande Id="10923" Montant="748,80" />
		<Commande Id="10924" Montant="1835,70" />
		<Commande Id="10925" Montant="475,15" />
		<Commande Id="10926" Montant="514,40" />
		<Commande Id="10927" Montant="800,00" />
		<Commande Id="10928" Montant="137,50" />
		<Commande Id="10929" Montant="1174,75" />
		<Commande Id="10930" Montant="2255,50" />
		<Commande Id="10931" Montant="799,20" />
		<Commande Id="10932" Montant="1788,63" />
		<Commande Id="10933" Montant="920,60" />
		<Commande Id="10934" Montant="500,00" />
		<Commande Id="10935" Montant="619,50" />
		<Commande Id="10936" Montant="456,00" />
		<Commande Id="10937" Montant="644,80" />
		<Commande Id="10938" Montant="2731,88" />
		<Commande Id="10939" Montant="637,50" />
		<Commande Id="10940" Montant="360,00" />
		<Commande Id="10941" Montant="4011,75" />
		<Commande Id="10942" Montant="560,00" />
		<Commande Id="10943" Montant="711,00" />
		<Commande Id="10944" Montant="1025,33" />
		<Commande Id="10945" Montant="245,00" />
		<Commande Id="10946" Montant="1407,50" />
		<Commande Id="10947" Montant="220,00" />
		<Commande Id="10948" Montant="2362,25" />
		<Commande Id="10949" Montant="4422,00" />
		<Commande Id="10950" Montant="110,00" />
		<Commande Id="10951" Montant="458,76" />
		<Commande Id="10952" Montant="471,20" />
		<Commande Id="10953" Montant="4441,25" />
		<Commande Id="10954" Montant="1659,54" />
		<Commande Id="10955" Montant="74,40" />
		<Commande Id="10956" Montant="677,00" />
		<Commande Id="10957" Montant="1762,70" />
		<Commande Id="10958" Montant="781,00" />
		<Commande Id="10959" Montant="131,75" />
		<Commande Id="10960" Montant="265,35" />
		<Commande Id="10961" Montant="1119,90" />
		<Commande Id="10962" Montant="3584,00" />
		<Commande Id="10963" Montant="57,80" />
		<Commande Id="10964" Montant="2052,50" />
		<Commande Id="10965" Montant="848,00" />
		<Commande Id="10966" Montant="1098,46" />
		<Commande Id="10967" Montant="910,40" />
		<Commande Id="10968" Montant="1408,00" />
		<Commande Id="10969" Montant="108,00" />
		<Commande Id="10970" Montant="224,00" />
		<Commande Id="10971" Montant="1733,06" />
		<Commande Id="10972" Montant="251,50" />
		<Commande Id="10973" Montant="291,55" />
		<Commande Id="10974" Montant="439,00" />
		<Commande Id="10975" Montant="717,50" />
		<Commande Id="10976" Montant="912,00" />
		<Commande Id="10977" Montant="2233,00" />
		<Commande Id="10978" Montant="1303,20" />
		<Commande Id="10979" Montant="4813,50" />
		<Commande Id="10980" Montant="248,00" />
		<Commande Id="10981" Montant="15810,00" />
		<Commande Id="10982" Montant="1014,00" />
		<Commande Id="10983" Montant="720,90" />
		<Commande Id="10984" Montant="1809,75" />
		<Commande Id="10985" Montant="2023,38" />
		<Commande Id="10986" Montant="2220,00" />
		<Commande Id="10987" Montant="2772,00" />
		<Commande Id="10988" Montant="3574,80" />
		<Commande Id="10989" Montant="1353,60" />
	</DateCommande>
	<DateCommande Année="1998" Mois="4">
		<Commande Id="10990" Montant="4288,85" />
		<Commande Id="10991" Montant="2296,00" />
		<Commande Id="10992" Montant="69,60" />
		<Commande Id="10993" Montant="4895,44" />
		<Commande Id="10994" Montant="940,50" />
		<Commande Id="10995" Montant="1196,00" />
		<Commande Id="10996" Montant="560,00" />
		<Commande Id="10997" Montant="1885,00" />
		<Commande Id="10998" Montant="686,00" />
		<Commande Id="10999" Montant="1197,95" />
		<Commande Id="11000" Montant="903,75" />
		<Commande Id="11001" Montant="2769,00" />
		<Commande Id="11002" Montant="1811,10" />
		<Commande Id="11003" Montant="326,00" />
		<Commande Id="11004" Montant="295,38" />
		<Commande Id="11005" Montant="586,00" />
		<Commande Id="11006" Montant="329,69" />
		<Commande Id="11007" Montant="2633,90" />
		<Commande Id="11008" Montant="4680,90" />
		<Commande Id="11009" Montant="616,50" />
		<Commande Id="11010" Montant="645,00" />
		<Commande Id="11011" Montant="933,50" />
		<Commande Id="11012" Montant="2825,30" />
		<Commande Id="11013" Montant="361,00" />
		<Commande Id="11014" Montant="243,18" />
		<Commande Id="11015" Montant="622,35" />
		<Commande Id="11016" Montant="491,50" />
		<Commande Id="11017" Montant="6750,00" />
		<Commande Id="11018" Montant="1575,00" />
		<Commande Id="11019" Montant="76,00" />
		<Commande Id="11020" Montant="632,40" />
		<Commande Id="11021" Montant="6306,24" />
		<Commande Id="11022" Montant="1402,00" />
		<Commande Id="11023" Montant="1500,00" />
		<Commande Id="11024" Montant="1966,81" />
		<Commande Id="11025" Montant="270,00" />
		<Commande Id="11026" Montant="1030,00" />
		<Commande Id="11027" Montant="877,73" />
		<Commande Id="11028" Montant="2160,00" />
		<Commande Id="11029" Montant="1286,80" />
		<Commande Id="11030" Montant="12615,05" />
		<Commande Id="11031" Montant="2393,50" />
		<Commande Id="11032" Montant="8902,50" />
		<Commande Id="11033" Montant="3232,80" />
		<Commande Id="11034" Montant="539,40" />
		<Commande Id="11035" Montant="1754,50" />
		<Commande Id="11036" Montant="1692,00" />
		<Commande Id="11037" Montant="60,00" />
		<Commande Id="11038" Montant="732,60" />
		<Commande Id="11039" Montant="3090,00" />
		<Commande Id="11040" Montant="200,00" />
		<Commande Id="11041" Montant="1773,00" />
		<Commande Id="11042" Montant="405,75" />
		<Commande Id="11043" Montant="210,00" />
		<Commande Id="11044" Montant="591,60" />
		<Commande Id="11045" Montant="1309,50" />
		<Commande Id="11046" Montant="1485,80" />
		<Commande Id="11047" Montant="817,88" />
		<Commande Id="11048" Montant="525,00" />
		<Commande Id="11049" Montant="273,60" />
		<Commande Id="11050" Montant="810,00" />
		<Commande Id="11051" Montant="36,00" />
		<Commande Id="11052" Montant="1332,00" />
		<Commande Id="11053" Montant="3055,00" />
		<Commande Id="11054" Montant="305,00" />
		<Commande Id="11055" Montant="1727,50" />
		<Commande Id="11056" Montant="3740,00" />
		<Commande Id="11057" Montant="45,00" />
		<Commande Id="11058" Montant="858,00" />
		<Commande Id="11059" Montant="1838,00" />
		<Commande Id="11060" Montant="266,00" />
		<Commande Id="11061" Montant="510,00" />
		<Commande Id="11062" Montant="406,40" />
		<Commande Id="11063" Montant="1342,95" />
	</DateCommande>
	<DateCommande Année="1998" Mois="5">
		<Commande Id="11064" Montant="4330,40" />
		<Commande Id="11065" Montant="189,42" />
		<Commande Id="11066" Montant="928,75" />
		<Commande Id="11067" Montant="86,85" />
		<Commande Id="11068" Montant="2027,08" />
		<Commande Id="11069" Montant="360,00" />
		<Commande Id="11070" Montant="1629,98" />
		<Commande Id="11071" Montant="484,50" />
		<Commande Id="11072" Montant="5218,00" />
		<Commande Id="11073" Montant="300,00" />
		<Commande Id="11074" Montant="232,09" />
		<Commande Id="11075" Montant="498,10" />
		<Commande Id="11076" Montant="792,75" />
		<Commande Id="11077" Montant="1255,72" />
	</DateCommande>
</DatesCommandes>